{
  "global": {
    "subheader-fontsize": {
      "value": "60",
      "type": "fontSizes"
    },
    "header-color": {
      "value": "#003ffc",
      "type": "color"
    },
    "name-text-color": {
      "value": "#07fc03",
      "type": "color"
    },
    "address-name-color": {
      "value": "#fc0303",
      "type": "color"
    },
    "mobile-color": {
      "value": "#fc0303",
      "type": "color"
    },
    "name_text_color": {
      "value": "#fb0000",
      "type": "color"
    }
  },
  "$themes": []
}